cast2md/__init__.py
cast2md/__main__.py
cast2md/cli.py
cast2md/main.py
cast2md/scheduler.py
cast2md/api/__init__.py
cast2md/api/episodes.py
cast2md/api/feeds.py
cast2md/api/itunes.py
cast2md/api/nodes.py
cast2md/api/queue.py
cast2md/api/runpod.py
cast2md/api/search.py
cast2md/api/settings.py
cast2md/api/system.py
cast2md/clients/__init__.py
cast2md/clients/itunes.py
cast2md/clients/pocketcasts.py
cast2md/config/__init__.py
cast2md/config/settings.py
cast2md/db/__init__.py
cast2md/db/config.py
cast2md/db/connection.py
cast2md/db/migrations.py
cast2md/db/models.py
cast2md/db/repository.py
cast2md/db/schema.py
cast2md/db/sql.py
cast2md/distributed/__init__.py
cast2md/distributed/coordinator.py
cast2md/download/__init__.py
cast2md/download/downloader.py
cast2md/export/__init__.py
cast2md/export/formats.py
cast2md/feed/__init__.py
cast2md/feed/discovery.py
cast2md/feed/itunes.py
cast2md/feed/parser.py
cast2md/mcp/__init__.py
cast2md/mcp/__main__.py
cast2md/mcp/client.py
cast2md/mcp/resources.py
cast2md/mcp/server.py
cast2md/mcp/tools.py
cast2md/node/__init__.py
cast2md/node/__main__.py
cast2md/node/config.py
cast2md/node/server.py
cast2md/node/worker.py
cast2md/notifications/__init__.py
cast2md/notifications/ntfy.py
cast2md/search/__init__.py
cast2md/search/embeddings.py
cast2md/search/parser.py
cast2md/search/repository.py
cast2md/services/__init__.py
cast2md/services/pod_setup.py
cast2md/services/runpod_service.py
cast2md/storage/__init__.py
cast2md/storage/filesystem.py
cast2md/transcription/__init__.py
cast2md/transcription/formats.py
cast2md/transcription/preprocessing.py
cast2md/transcription/service.py
cast2md/transcription/providers/__init__.py
cast2md/transcription/providers/base.py
cast2md/transcription/providers/pocketcasts.py
cast2md/transcription/providers/podcast20.py
cast2md/web/__init__.py
cast2md/web/views.py
cast2md/worker/__init__.py
cast2md/worker/manager.py
cast2md-2026.1.1.dist-info/licenses/LICENSE
cast2md-2026.1.1.dist-info/METADATA
cast2md-2026.1.1.dist-info/WHEEL
cast2md-2026.1.1.dist-info/entry_points.txt
cast2md-2026.1.1.dist-info/top_level.txt
cast2md-2026.1.1.dist-info/RECORD
