Metadata-Version: 2.4
Name: cast2md
Version: 2026.1.1
Summary: Podcast transcription service - download episodes via RSS and transcribe with Whisper
Author: cast2md
License: MIT
Classifier: Development Status :: 3 - Alpha
Classifier: Intended Audience :: End Users/Desktop
Classifier: License :: OSI Approved :: MIT License
Classifier: Programming Language :: Python :: 3
Classifier: Programming Language :: Python :: 3.11
Classifier: Programming Language :: Python :: 3.12
Requires-Python: >=3.11
License-File: LICENSE
Requires-Dist: feedparser>=6.0.0
Requires-Dist: httpx[socks]>=0.26.0
Requires-Dist: faster-whisper>=1.0.0
Requires-Dist: pydantic-settings>=2.0.0
Requires-Dist: python-dotenv>=1.0.0
Requires-Dist: click>=8.1.0
Requires-Dist: fastapi>=0.109.0
Requires-Dist: uvicorn[standard]>=0.27.0
Requires-Dist: jinja2>=3.1.0
Requires-Dist: apscheduler>=3.10.0
Requires-Dist: bleach>=6.0
Requires-Dist: mcp[cli]>=1.2.0
Requires-Dist: sentence-transformers>=2.2.0
Requires-Dist: psycopg2-binary>=2.9.0
Requires-Dist: pgvector>=0.2.0
Requires-Dist: runpod>=1.6.0
Provides-Extra: dev
Requires-Dist: pytest>=7.0.0; extra == "dev"
Requires-Dist: pytest-asyncio>=0.23.0; extra == "dev"
Requires-Dist: ruff>=0.1.0; extra == "dev"
Provides-Extra: mlx
Requires-Dist: mlx-whisper>=0.4.0; extra == "mlx"
Provides-Extra: node
Requires-Dist: httpx[socks]>=0.26.0; extra == "node"
Requires-Dist: faster-whisper>=1.0.0; extra == "node"
Requires-Dist: pydantic-settings>=2.0.0; extra == "node"
Requires-Dist: python-dotenv>=1.0.0; extra == "node"
Requires-Dist: click>=8.1.0; extra == "node"
Requires-Dist: fastapi>=0.109.0; extra == "node"
Requires-Dist: uvicorn[standard]>=0.27.0; extra == "node"
Requires-Dist: jinja2>=3.1.0; extra == "node"
Provides-Extra: node-mlx
Requires-Dist: mlx-whisper>=0.4.0; extra == "node-mlx"
Dynamic: license-file
